emtd/__init__.py
emtd/emtd.py
emtd-0.3.1.dist-info/LICENSE.txt
emtd-0.3.1.dist-info/METADATA
emtd-0.3.1.dist-info/WHEEL
emtd-0.3.1.dist-info/top_level.txt
emtd-0.3.1.dist-info/RECORD
