Metadata-Version: 2.1
Name: emtd
Version: 0.3.1
Summary: This projects provides as slim Python wrapper to access the 'technology-data' data set / snakemake workflow, maintained by the PyPSA team.
Author-email: sstroemer <stefan.stroemer@gmail.com>
License: MIT
Project-URL: repository, https://github.com/sstroemer/emtd
Keywords: energy modeling,technology data
Requires-Python: <3.13,>=3.11
License-File: LICENSE.txt
Requires-Dist: pandas<3.0,>=2.1
Requires-Dist: snakemake<9.0,>=8.5
Requires-Dist: openpyxl<4.0,>=3.1.2
Requires-Dist: beautifulsoup4<5.0,>=4.12
Requires-Dist: numpy<2.0,>=1.26
Requires-Dist: xlrd<3.0,>=2.0
Requires-Dist: scipy<2.0,>=1.14.0
Requires-Dist: packaging<24.0,>=23.0
Requires-Dist: currencyconverter
Requires-Dist: tabula-py<3.0,>=2.10
Requires-Dist: pathlib<2.0,>=1.0
Requires-Dist: pyyaml<7.0,>=6.0
